gmshairfoil2d/__init__.py
gmshairfoil2d/airfoil_func.py
gmshairfoil2d/geometry_def.py
gmshairfoil2d/gmshairfoil2d.py
gmshairfoil2d-0.2.2.dist-info/licenses/LICENSE
tests/__init__.py
tests/test_airfoil_func.py
tests/test_geometry_def.py
gmshairfoil2d-0.2.2.dist-info/METADATA
gmshairfoil2d-0.2.2.dist-info/WHEEL
gmshairfoil2d-0.2.2.dist-info/entry_points.txt
gmshairfoil2d-0.2.2.dist-info/top_level.txt
gmshairfoil2d-0.2.2.dist-info/RECORD
