Metadata-Version: 2.4
Name: gmshairfoil2d
Version: 0.2.2
Summary: Python tool to generate 2D mesh around an airfoil
Home-page: https://github.com/cfsengineering/GMSH-Airfoil-2D
Author: Giacomo Benedetti
Author-email: giacomo.benedetti@cfse.ch
Keywords: airfoil,2D,mesh,cfd,gmsh
Classifier: Programming Language :: Python :: 3.11
Classifier: License :: OSI Approved :: Apache Software License
Classifier: Operating System :: OS Independent
Classifier: Intended Audience :: Developers
Requires-Python: >=3.11.0
License-File: LICENSE
Requires-Dist: gmsh>=4.14
Requires-Dist: numpy>=1.20.3
Requires-Dist: pytest==7.1.3
Requires-Dist: requests==2.26.0
Dynamic: author
Dynamic: author-email
Dynamic: classifier
Dynamic: description
Dynamic: description-content-type
Dynamic: home-page
Dynamic: keywords
Dynamic: license-file
Dynamic: requires-dist
Dynamic: requires-python
Dynamic: summary
